argparse_param_types/__init__.py
argparse_param_types/argparse_param_types.py
argparse_param_types-0.0.3.dist-info/METADATA
argparse_param_types-0.0.3.dist-info/WHEEL
argparse_param_types-0.0.3.dist-info/licenses/LICENSE
argparse_param_types-0.0.3.dist-info/RECORD
