Metadata-Version: 2.1
Name: argparse-param-types
Version: 0.0.3
Summary: Provides a library of common option types for the argparse cammand-line options parser
Project-URL: Homepage, https://github.com/ndmalc/argparse_param_types
Project-URL: Bug Tracker, https://github.com/ndmalc/argparse_param_types/issues
Author: ndmalc
License: MIT License
License-File: LICENSE
Classifier: License :: OSI Approved :: MIT License
Classifier: Operating System :: OS Independent
Classifier: Programming Language :: Python :: 3
Requires-Python: >=3
Requires-Dist: ipaddress
Requires-Dist: regex
Provides-Extra: tests
Requires-Dist: pyfakefs; extra == 'tests'
Requires-Dist: pytest; extra == 'tests'
